bitsandbytes/__init__.py
bitsandbytes/functional.py
bitsandbytes/libbitsandbytes.so
bitsandbytes/nn/__init__.py
bitsandbytes/nn/modules.py
bitsandbytes/optim/__init__.py
bitsandbytes/optim/adagrad.py
bitsandbytes/optim/adam.py
bitsandbytes/optim/adamw.py
bitsandbytes/optim/lamb.py
bitsandbytes/optim/lars.py
bitsandbytes/optim/optimizer.py
bitsandbytes/optim/rmsprop.py
bitsandbytes/optim/sgd.py
bitsandbytes_cuda115-0.26.0.post2.dist-info/LICENSE
bitsandbytes_cuda115-0.26.0.post2.dist-info/METADATA
bitsandbytes_cuda115-0.26.0.post2.dist-info/NOTICE.md
bitsandbytes_cuda115-0.26.0.post2.dist-info/WHEEL
bitsandbytes_cuda115-0.26.0.post2.dist-info/top_level.txt
bitsandbytes_cuda115-0.26.0.post2.dist-info/RECORD
