Metadata-Version: 2.1
Name: bitsandbytes-cuda115
Version: 0.26.0.post2
Summary: 8-bit optimizers and quantization routines.
Home-page: http://packages.python.org/bitsandbytes
Author: Tim Dettmers
Author-email: dettmers@cs.washington.edu
License: MIT
Keywords: gpu optimizers optimization 8-bit quantization compression
Classifier: Development Status :: 4 - Beta
Classifier: Topic :: Scientific/Engineering :: Artificial Intelligence
License-File: LICENSE
License-File: NOTICE.md
